[{"Fecha":"09\/16\/2021","Nombre del Producto":"Gorro (M, Gris, Patagonia)","Cantidad Vendida":8,"Precio Unitario":20,"Total de Venta":"$100.00","Categor\u00eda":"Accesorios","Regi\u00f3n":"Norte"},{"Fecha":"12\/06\/2020","Nombre del Producto":"Sudadera (L, Roja, Under Armour)","Cantidad Vendida":2,"Precio Unitario":40,"Total de Venta":"$120.00","Categor\u00eda":"Ropa","Regi\u00f3n":"Sur"},{"Fecha":"04\/23\/2020","Nombre del Producto":"Reloj (\u00danico, Plata, Casio)","Cantidad Vendida":6,"Precio Unitario":60,"Total de Venta":"$120.00","Categor\u00eda":"Accesorios","Regi\u00f3n":"Este"},{"Fecha":"12\/26\/2022","Nombre del Producto":"Mochila (M, Negra, North Face)","Cantidad Vendida":4,"Precio Unitario":80,"Total de Venta":"$320.00","Categor\u00eda":"Accesorios","Regi\u00f3n":"Norte"},{"Fecha":"06\/21\/2024","Nombre del Producto":"Gorra (\u00danico, Azul, Nike)","Cantidad Vendida":9,"Precio Unitario":15,"Total de Venta":"$105.00","Categor\u00eda":"Accesorios","Regi\u00f3n":"Sur"},{"Fecha":"11\/06\/2022","Nombre del Producto":"Chaqueta (M, Negra, Columbia)","Cantidad Vendida":9,"Precio Unitario":100,"Total de Venta":"$200.00","Categor\u00eda":"Ropa","Regi\u00f3n":"Norte"},{"Fecha":"08\/06\/2023","Nombre del Producto":"Calcetines (L, Blanco, Puma)","Cantidad Vendida":10,"Precio Unitario":5,"Total de Venta":"$50.00","Categor\u00eda":"Accesorios","Regi\u00f3n":"Este"},{"Fecha":"12\/30\/2022","Nombre del Producto":"Bufanda (\u00danica, Roja, Gucci)","Cantidad Vendida":7,"Precio Unitario":150,"Total de Venta":"$150.00","Categor\u00eda":"Accesorios","Regi\u00f3n":"Sur"},{"Fecha":"07\/09\/2021","Nombre del Producto":"Botas (43, Marr\u00f3n, Dr. Martens)","Cantidad Vendida":2,"Precio Unitario":120,"Total de Venta":"$360.00","Categor\u00eda":"Calzado","Regi\u00f3n":"Norte"},{"Fecha":"03\/02\/2023","Nombre del Producto":"Traje (M, Azul, Armani)","Cantidad Vendida":7,"Precio Unitario":300,"Total de Venta":"$300.00","Categor\u00eda":"Ropa","Regi\u00f3n":"Este"},{"Fecha":"04\/28\/2022","Nombre del Producto":"Vestido (L, Verde, Zara)","Cantidad Vendida":7,"Precio Unitario":45,"Total de Venta":"$90.00","Categor\u00eda":"Ropa","Regi\u00f3n":"Sur"},{"Fecha":"06\/18\/2024","Nombre del Producto":"Sandalias (38, Negro, Birkenstock)","Cantidad Vendida":1,"Precio Unitario":35,"Total de Venta":"$210.00","Categor\u00eda":"Calzado","Regi\u00f3n":"Norte"},{"Fecha":"12\/02\/2020","Nombre del Producto":"Gafas de Sol (\u00danico, Negro, Ray-Ban)","Cantidad Vendida":4,"Precio Unitario":120,"Total de Venta":"$360.00","Categor\u00eda":"Accesorios","Regi\u00f3n":"Este"},{"Fecha":"04\/28\/2024","Nombre del Producto":"Guantes (M, Negro, Reebok)","Cantidad Vendida":1,"Precio Unitario":25,"Total de Venta":"$200.00","Categor\u00eda":"Accesorios","Regi\u00f3n":"Sur"},{"Fecha":"10\/17\/2023","Nombre del Producto":"Corbata (\u00danica, Roja, Hugo Boss)","Cantidad Vendida":9,"Precio Unitario":30,"Total de Venta":"$150.00","Categor\u00eda":"Accesorios","Regi\u00f3n":"Norte"},{"Fecha":"02\/18\/2023","Nombre del Producto":"Falda (S, Negra, H&M)","Cantidad Vendida":2,"Precio Unitario":35,"Total de Venta":"$140.00","Categor\u00eda":"Ropa","Regi\u00f3n":"Este"},{"Fecha":"03\/22\/2024","Nombre del Producto":"Chaqueta (L, Verde, Patagonia)","Cantidad Vendida":10,"Precio Unitario":150,"Total de Venta":"$300.00","Categor\u00eda":"Ropa","Regi\u00f3n":"Norte"},{"Fecha":"12\/26\/2022","Nombre del Producto":"Maleta (M, Azul, Samsonite)","Cantidad Vendida":2,"Precio Unitario":100,"Total de Venta":"$300.00","Categor\u00eda":"Accesorios","Regi\u00f3n":"Sur"},{"Fecha":"04\/23\/2024","Nombre del Producto":"Zapatos de Deporte (40, Blanco, New Balance)","Cantidad Vendida":3,"Precio Unitario":70,"Total de Venta":"$350.00","Categor\u00eda":"Calzado","Regi\u00f3n":"Este"},{"Fecha":"07\/21\/2023","Nombre del Producto":"Paraguas (\u00danico, Negro, Totes)","Cantidad Vendida":3,"Precio Unitario":25,"Total de Venta":"$150.00","Categor\u00eda":"Accesorios","Regi\u00f3n":"Norte"},{"Fecha":"11\/17\/2022","Nombre del Producto":"Zapatos (41, Negro, Nike)","Cantidad Vendida":1,"Precio Unitario":50,"Total de Venta":"$50.00","Categor\u00eda":"Calzado","Regi\u00f3n":"Norte"},{"Fecha":"03\/18\/2020","Nombre del Producto":"Camiseta (S, Negra, Adidas)","Cantidad Vendida":3,"Precio Unitario":15,"Total de Venta":"$15.00","Categor\u00eda":"Ropa","Regi\u00f3n":"Este"},{"Fecha":"06\/19\/2024","Nombre del Producto":"Camiseta (M, Azul, Nike)","Cantidad Vendida":2,"Precio Unitario":15,"Total de Venta":"$60.00","Categor\u00eda":"Ropa","Regi\u00f3n":"Norte"},{"Fecha":"03\/21\/2021","Nombre del Producto":"Pantal\u00f3n (L, Gris, Levi's)","Cantidad Vendida":6,"Precio Unitario":25,"Total de Venta":"$150.00","Categor\u00eda":"Ropa","Regi\u00f3n":"Este"},{"Fecha":"05\/28\/2021","Nombre del Producto":"Zapatos (42, Negro, Nike)","Cantidad Vendida":6,"Precio Unitario":50,"Total de Venta":"$450.00","Categor\u00eda":"Calzado","Regi\u00f3n":"Norte"},{"Fecha":"09\/21\/2021","Nombre del Producto":"Gorro (M, Gris, Patagonia)","Cantidad Vendida":5,"Precio Unitario":20,"Total de Venta":"$100.00","Categor\u00eda":"Accesorios","Regi\u00f3n":"Norte"},{"Fecha":"01\/14\/2023","Nombre del Producto":"Sudadera (L, Roja, Under Armour)","Cantidad Vendida":1,"Precio Unitario":40,"Total de Venta":"$120.00","Categor\u00eda":"Ropa","Regi\u00f3n":"Sur"},{"Fecha":"03\/10\/2021","Nombre del Producto":"Reloj (\u00danico, Plata, Casio)","Cantidad Vendida":5,"Precio Unitario":60,"Total de Venta":"$120.00","Categor\u00eda":"Accesorios","Regi\u00f3n":"Este"},{"Fecha":"02\/19\/2021","Nombre del Producto":"Mochila (M, Negra, North Face)","Cantidad Vendida":7,"Precio Unitario":80,"Total de Venta":"$320.00","Categor\u00eda":"Accesorios","Regi\u00f3n":"Norte"},{"Fecha":"09\/06\/2020","Nombre del Producto":"Gorra (\u00danico, Azul, Nike)","Cantidad Vendida":2,"Precio Unitario":15,"Total de Venta":"$105.00","Categor\u00eda":"Accesorios","Regi\u00f3n":"Sur"},{"Fecha":"07\/23\/2023","Nombre del Producto":"Chaqueta (M, Negra, Columbia)","Cantidad Vendida":3,"Precio Unitario":100,"Total de Venta":"$200.00","Categor\u00eda":"Ropa","Regi\u00f3n":"Norte"},{"Fecha":"07\/19\/2020","Nombre del Producto":"Calcetines (L, Blanco, Puma)","Cantidad Vendida":1,"Precio Unitario":5,"Total de Venta":"$50.00","Categor\u00eda":"Accesorios","Regi\u00f3n":"Este"},{"Fecha":"05\/03\/2023","Nombre del Producto":"Bufanda (\u00danica, Roja, Gucci)","Cantidad Vendida":7,"Precio Unitario":150,"Total de Venta":"$150.00","Categor\u00eda":"Accesorios","Regi\u00f3n":"Sur"},{"Fecha":"08\/08\/2020","Nombre del Producto":"Botas (43, Marr\u00f3n, Dr. Martens)","Cantidad Vendida":5,"Precio Unitario":120,"Total de Venta":"$360.00","Categor\u00eda":"Calzado","Regi\u00f3n":"Norte"},{"Fecha":"11\/02\/2021","Nombre del Producto":"Traje (M, Azul, Armani)","Cantidad Vendida":7,"Precio Unitario":300,"Total de Venta":"$300.00","Categor\u00eda":"Ropa","Regi\u00f3n":"Este"},{"Fecha":"04\/07\/2023","Nombre del Producto":"Vestido (L, Verde, Zara)","Cantidad Vendida":9,"Precio Unitario":45,"Total de Venta":"$90.00","Categor\u00eda":"Ropa","Regi\u00f3n":"Sur"},{"Fecha":"02\/09\/2020","Nombre del Producto":"Sandalias (38, Negro, Birkenstock)","Cantidad Vendida":7,"Precio Unitario":35,"Total de Venta":"$210.00","Categor\u00eda":"Calzado","Regi\u00f3n":"Norte"},{"Fecha":"12\/03\/2021","Nombre del Producto":"Gafas de Sol (\u00danico, Negro, Ray-Ban)","Cantidad Vendida":9,"Precio Unitario":120,"Total de Venta":"$360.00","Categor\u00eda":"Accesorios","Regi\u00f3n":"Este"},{"Fecha":"04\/16\/2021","Nombre del Producto":"Guantes (M, Negro, Reebok)","Cantidad Vendida":5,"Precio Unitario":25,"Total de Venta":"$200.00","Categor\u00eda":"Accesorios","Regi\u00f3n":"Sur"},{"Fecha":"12\/15\/2022","Nombre del Producto":"Corbata (\u00danica, Roja, Hugo Boss)","Cantidad Vendida":1,"Precio Unitario":30,"Total de Venta":"$150.00","Categor\u00eda":"Accesorios","Regi\u00f3n":"Norte"},{"Fecha":"06\/20\/2024","Nombre del Producto":"Falda (S, Negra, H&M)","Cantidad Vendida":5,"Precio Unitario":35,"Total de Venta":"$140.00","Categor\u00eda":"Ropa","Regi\u00f3n":"Este"},{"Fecha":"11\/13\/2022","Nombre del Producto":"Chaqueta (L, Verde, Patagonia)","Cantidad Vendida":9,"Precio Unitario":150,"Total de Venta":"$300.00","Categor\u00eda":"Ropa","Regi\u00f3n":"Norte"},{"Fecha":"01\/25\/2020","Nombre del Producto":"Maleta (M, Azul, Samsonite)","Cantidad Vendida":4,"Precio Unitario":100,"Total de Venta":"$300.00","Categor\u00eda":"Accesorios","Regi\u00f3n":"Sur"},{"Fecha":"12\/20\/2021","Nombre del Producto":"Zapatos de Deporte (40, Blanco, New Balance)","Cantidad Vendida":2,"Precio Unitario":70,"Total de Venta":"$350.00","Categor\u00eda":"Calzado","Regi\u00f3n":"Este"},{"Fecha":"10\/29\/2023","Nombre del Producto":"Paraguas (\u00danico, Negro, Totes)","Cantidad Vendida":6,"Precio Unitario":25,"Total de Venta":"$150.00","Categor\u00eda":"Accesorios","Regi\u00f3n":"Norte"},{"Fecha":"03\/05\/2024","Nombre del Producto":"Zapatos (41, Negro, Nike)","Cantidad Vendida":5,"Precio Unitario":50,"Total de Venta":"$50.00","Categor\u00eda":"Calzado","Regi\u00f3n":"Norte"},{"Fecha":"01\/23\/2022","Nombre del Producto":"Camiseta (S, Negra, Adidas)","Cantidad Vendida":6,"Precio Unitario":15,"Total de Venta":"$15.00","Categor\u00eda":"Ropa","Regi\u00f3n":"Este"},{"Fecha":"04\/24\/2024","Nombre del Producto":"Camiseta (M, Azul, Nike)","Cantidad Vendida":6,"Precio Unitario":15,"Total de Venta":"$60.00","Categor\u00eda":"Ropa","Regi\u00f3n":"Norte"},{"Fecha":"04\/12\/2023","Nombre del Producto":"Pantal\u00f3n (L, Gris, Levi's)","Cantidad Vendida":8,"Precio Unitario":25,"Total de Venta":"$150.00","Categor\u00eda":"Ropa","Regi\u00f3n":"Este"},{"Fecha":"05\/05\/2021","Nombre del Producto":"Zapatos (42, Negro, Nike)","Cantidad Vendida":8,"Precio Unitario":50,"Total de Venta":"$450.00","Categor\u00eda":"Calzado","Regi\u00f3n":"Norte"},{"Fecha":"01\/19\/2021","Nombre del Producto":"Gorro (M, Gris, Patagonia)","Cantidad Vendida":5,"Precio Unitario":20,"Total de Venta":"$100.00","Categor\u00eda":"Accesorios","Regi\u00f3n":"Norte"},{"Fecha":"09\/12\/2021","Nombre del Producto":"Sudadera (L, Roja, Under Armour)","Cantidad Vendida":7,"Precio Unitario":40,"Total de Venta":"$120.00","Categor\u00eda":"Ropa","Regi\u00f3n":"Sur"},{"Fecha":"11\/05\/2021","Nombre del Producto":"Reloj (\u00danico, Plata, Casio)","Cantidad Vendida":2,"Precio Unitario":60,"Total de Venta":"$120.00","Categor\u00eda":"Accesorios","Regi\u00f3n":"Este"},{"Fecha":"02\/19\/2020","Nombre del Producto":"Mochila (M, Negra, North Face)","Cantidad Vendida":1,"Precio Unitario":80,"Total de Venta":"$320.00","Categor\u00eda":"Accesorios","Regi\u00f3n":"Norte"},{"Fecha":"03\/15\/2022","Nombre del Producto":"Gorra (\u00danico, Azul, Nike)","Cantidad Vendida":6,"Precio Unitario":15,"Total de Venta":"$105.00","Categor\u00eda":"Accesorios","Regi\u00f3n":"Sur"},{"Fecha":"07\/02\/2024","Nombre del Producto":"Chaqueta (M, Negra, Columbia)","Cantidad Vendida":5,"Precio Unitario":100,"Total de Venta":"$200.00","Categor\u00eda":"Ropa","Regi\u00f3n":"Norte"},{"Fecha":"06\/05\/2020","Nombre del Producto":"Calcetines (L, Blanco, Puma)","Cantidad Vendida":10,"Precio Unitario":5,"Total de Venta":"$50.00","Categor\u00eda":"Accesorios","Regi\u00f3n":"Este"},{"Fecha":"05\/05\/2022","Nombre del Producto":"Bufanda (\u00danica, Roja, Gucci)","Cantidad Vendida":2,"Precio Unitario":150,"Total de Venta":"$150.00","Categor\u00eda":"Accesorios","Regi\u00f3n":"Sur"},{"Fecha":"04\/21\/2022","Nombre del Producto":"Botas (43, Marr\u00f3n, Dr. Martens)","Cantidad Vendida":10,"Precio Unitario":120,"Total de Venta":"$360.00","Categor\u00eda":"Calzado","Regi\u00f3n":"Norte"},{"Fecha":"06\/28\/2024","Nombre del Producto":"Traje (M, Azul, Armani)","Cantidad Vendida":6,"Precio Unitario":300,"Total de Venta":"$300.00","Categor\u00eda":"Ropa","Regi\u00f3n":"Este"},{"Fecha":"11\/02\/2020","Nombre del Producto":"Vestido (L, Verde, Zara)","Cantidad Vendida":9,"Precio Unitario":45,"Total de Venta":"$90.00","Categor\u00eda":"Ropa","Regi\u00f3n":"Sur"},{"Fecha":"09\/13\/2020","Nombre del Producto":"Sandalias (38, Negro, Birkenstock)","Cantidad Vendida":9,"Precio Unitario":35,"Total de Venta":"$210.00","Categor\u00eda":"Calzado","Regi\u00f3n":"Norte"},{"Fecha":"01\/09\/2024","Nombre del Producto":"Gafas de Sol (\u00danico, Negro, Ray-Ban)","Cantidad Vendida":7,"Precio Unitario":120,"Total de Venta":"$360.00","Categor\u00eda":"Accesorios","Regi\u00f3n":"Este"},{"Fecha":"07\/29\/2023","Nombre del Producto":"Guantes (M, Negro, Reebok)","Cantidad Vendida":10,"Precio Unitario":25,"Total de Venta":"$200.00","Categor\u00eda":"Accesorios","Regi\u00f3n":"Sur"},{"Fecha":"12\/20\/2023","Nombre del Producto":"Corbata (\u00danica, Roja, Hugo Boss)","Cantidad Vendida":10,"Precio Unitario":30,"Total de Venta":"$150.00","Categor\u00eda":"Accesorios","Regi\u00f3n":"Norte"},{"Fecha":"01\/01\/2024","Nombre del Producto":"Falda (S, Negra, H&M)","Cantidad Vendida":8,"Precio Unitario":35,"Total de Venta":"$140.00","Categor\u00eda":"Ropa","Regi\u00f3n":"Este"},{"Fecha":"08\/16\/2020","Nombre del Producto":"Chaqueta (L, Verde, Patagonia)","Cantidad Vendida":8,"Precio Unitario":150,"Total de Venta":"$300.00","Categor\u00eda":"Ropa","Regi\u00f3n":"Norte"},{"Fecha":"04\/22\/2020","Nombre del Producto":"Maleta (M, Azul, Samsonite)","Cantidad Vendida":9,"Precio Unitario":100,"Total de Venta":"$300.00","Categor\u00eda":"Accesorios","Regi\u00f3n":"Sur"},{"Fecha":"02\/27\/2020","Nombre del Producto":"Zapatos de Deporte (40, Blanco, New Balance)","Cantidad Vendida":7,"Precio Unitario":70,"Total de Venta":"$350.00","Categor\u00eda":"Calzado","Regi\u00f3n":"Este"},{"Fecha":"09\/23\/2020","Nombre del Producto":"Paraguas (\u00danico, Negro, Totes)","Cantidad Vendida":1,"Precio Unitario":25,"Total de Venta":"$150.00","Categor\u00eda":"Accesorios","Regi\u00f3n":"Norte"},{"Fecha":"02\/24\/2022","Nombre del Producto":"Zapatos (41, Negro, Nike)","Cantidad Vendida":1,"Precio Unitario":50,"Total de Venta":"$50.00","Categor\u00eda":"Calzado","Regi\u00f3n":"Norte"},{"Fecha":"03\/16\/2024","Nombre del Producto":"Camiseta (S, Negra, Adidas)","Cantidad Vendida":7,"Precio Unitario":15,"Total de Venta":"$15.00","Categor\u00eda":"Ropa","Regi\u00f3n":"Este"},{"Fecha":"07\/15\/2021","Nombre del Producto":"Camiseta (M, Azul, Nike)","Cantidad Vendida":3,"Precio Unitario":15,"Total de Venta":"$60.00","Categor\u00eda":"Ropa","Regi\u00f3n":"Norte"},{"Fecha":"07\/08\/2020","Nombre del Producto":"Pantal\u00f3n (L, Gris, Levi's)","Cantidad Vendida":6,"Precio Unitario":25,"Total de Venta":"$150.00","Categor\u00eda":"Ropa","Regi\u00f3n":"Este"},{"Fecha":"10\/01\/2021","Nombre del Producto":"Zapatos (42, Negro, Nike)","Cantidad Vendida":7,"Precio Unitario":50,"Total de Venta":"$450.00","Categor\u00eda":"Calzado","Regi\u00f3n":"Norte"}]